tests/tests/__init__.py
tests/tests/exception/__init__.py
tests/tests/exception/test_get_message.py
tests/tests/exception/test_get_template.py
tests/tests/exception/test_init.py
tests/tests/exception/test_str.py
xcept/__init__.py
xcept/exception.py
xcept/warnings.py
xcept/formatter/__init__.py
xcept/formatter/formatter.py
xcept/formatter/helpers.py
xcept/formatter/formatters/__init__.py
xcept/formatter/formatters/hard.py
xcept/formatter/formatters/soft.py
xcept-3.1.0.dist-info/LICENSE
xcept-3.1.0.dist-info/METADATA
xcept-3.1.0.dist-info/WHEEL
xcept-3.1.0.dist-info/top_level.txt
xcept-3.1.0.dist-info/RECORD
